LICENSE.txt
MANIFEST.in
README.md
setup.py
steepdata/__init__.py
steepdata/helpers.py
steepdata/steemdata.py
steepdata/utils.py
steepdata.egg-info/PKG-INFO
steepdata.egg-info/SOURCES.txt
steepdata.egg-info/dependency_links.txt
steepdata.egg-info/requires.txt
steepdata.egg-info/top_level.txt