Metadata-Version: 1.1
Name: steepdata
Version: 0.0.3
Summary: Python Utilities for parsing STEEM blockchain
Home-page: https://github.com/Chainers/steepdata
Author: @steepshot
Author-email: steepshot.org@gmail.com
License: The MIT License (MIT)
